_substance_painter-stubs/__init__.pyi
_substance_painter-stubs/analytics.pyi
_substance_painter-stubs/baking.pyi
_substance_painter-stubs/data_tweak.pyi
_substance_painter-stubs/display.pyi
_substance_painter-stubs/event.pyi
_substance_painter-stubs/exception.pyi
_substance_painter-stubs/export.pyi
_substance_painter-stubs/feature.pyi
_substance_painter-stubs/fiber.pyi
_substance_painter-stubs/interop.pyi
_substance_painter-stubs/js.pyi
_substance_painter-stubs/logging.pyi
_substance_painter-stubs/project.pyi
_substance_painter-stubs/resource.pyi
_substance_painter-stubs/textureset.pyi
_substance_painter-stubs/ui.pyi
substance_painter-stubs/__init__.pyi
substance_painter-stubs/_executor.pyi
substance_painter-stubs/_utility.pyi
substance_painter-stubs/_version.pyi
substance_painter-stubs/application.pyi
substance_painter-stubs/baking.pyi
substance_painter-stubs/display.pyi
substance_painter-stubs/event.pyi
substance_painter-stubs/exception.pyi
substance_painter-stubs/export.pyi
substance_painter-stubs/js.pyi
substance_painter-stubs/logging.pyi
substance_painter-stubs/project.pyi
substance_painter-stubs/properties.pyi
substance_painter-stubs/resource.pyi
substance_painter-stubs/textureset.pyi
substance_painter-stubs/ui.pyi
types_substance_painter-2023.8.3.0.0.dist-info/METADATA
types_substance_painter-2023.8.3.0.0.dist-info/WHEEL
types_substance_painter-2023.8.3.0.0.dist-info/RECORD
